in_azure/__init__.py
in_azure/funcs.py
tests/__init__.py
tests/test_funcs.py
infteamflevev-0.0.1.dist-info/METADATA
infteamflevev-0.0.1.dist-info/WHEEL
infteamflevev-0.0.1.dist-info/top_level.txt
infteamflevev-0.0.1.dist-info/RECORD
