Metadata-Version: 2.1
Name: infteamflevev
Version: 0.0.1
Summary: Azure Python library
Author: Infinity Team
